qiskit_mps_initializer/__init__.py
qiskit_mps_initializer/py.typed
qiskit_mps_initializer/circuit/__init__.py
qiskit_mps_initializer/circuit/mps_initializer.py
qiskit_mps_initializer/datatypes/__init__.py
qiskit_mps_initializer/datatypes/quantum_intensity.py
qiskit_mps_initializer/datatypes/quantum_state.py
qiskit_mps_initializer/helpers/__init__.py
qiskit_mps_initializer/helpers/extractors.py
qiskit_mps_initializer/helpers/mps_technique.py
qiskit_mps_initializer/helpers/sampling_and_data_preperation.py
qiskit_mps_initializer/utils/__init__.py
qiskit_mps_initializer/utils/simulation.py
qiskit_mps_initializer-0.2.4.dist-info/METADATA
qiskit_mps_initializer-0.2.4.dist-info/WHEEL
qiskit_mps_initializer-0.2.4.dist-info/licenses/LICENSE
qiskit_mps_initializer-0.2.4.dist-info/RECORD
