Metadata-Version: 2.4
Name: qiskit-mps-initializer
Version: 0.2.4
Summary: Wavefunction initializers for Qiskit based on matrix product states (MPS)
Project-URL: Homepage, https://github.com/BlackWild/qiskit-mps-initializer
Project-URL: Documentation, https://blackwild.github.io/qiskit-mps-initializer/
Author-email: Siavash Davani <siavash.davani@uni-jena.de>
License-Expression: MIT
License-File: LICENSE
Classifier: Development Status :: 3 - Alpha
Classifier: Intended Audience :: Science/Research
Classifier: Operating System :: MacOS
Classifier: Operating System :: Microsoft :: Windows
Classifier: Operating System :: POSIX :: Linux
Classifier: Programming Language :: Python
Classifier: Programming Language :: Python :: 3
Classifier: Programming Language :: Python :: 3 :: Only
Classifier: Topic :: Scientific/Engineering
Classifier: Topic :: Scientific/Engineering :: Physics
Requires-Python: >=3.10
Requires-Dist: pydantic>=2.11.5
Requires-Dist: qiskit-aer>=0.17.1
Requires-Dist: qiskit>=2.0.1
Requires-Dist: quimb>=1.11.0
